romanify/__init__.py
romanify/main.py
romanify-0.0.8.dist-info/LICENSE
romanify-0.0.8.dist-info/METADATA
romanify-0.0.8.dist-info/WHEEL
romanify-0.0.8.dist-info/entry_points.txt
romanify-0.0.8.dist-info/top_level.txt
romanify-0.0.8.dist-info/RECORD
